cylouvain/__init__.py
cylouvain/_louvain.cpython-36m-darwin.so
cylouvain-0.2.1.dist-info/DESCRIPTION.rst
cylouvain-0.2.1.dist-info/METADATA
cylouvain-0.2.1.dist-info/RECORD
cylouvain-0.2.1.dist-info/WHEEL
cylouvain-0.2.1.dist-info/metadata.json
cylouvain-0.2.1.dist-info/top_level.txt
