Metadata-Version: 2.0
Name: cylouvain
Version: 0.2.1
Summary: Cython implementation of the classic Louvain algorithm for community detection in graphs
Home-page: http://github.com/ahollocou/cylouvain
Author: Alexandre Hollocou
Author-email: alexandre@hollocou.fr
License: new BSD
Platform: UNKNOWN
Requires-Dist: numpy
Requires-Dist: scipy
Requires-Dist: networkx
